gradio/.dockerignore
gradio/__init__.py
gradio/analytics.py
gradio/blocks.py
gradio/components.py
gradio/context.py
gradio/data_classes.py
gradio/deprecation.py
gradio/events.py
gradio/exceptions.py
gradio/external.py
gradio/external_utils.py
gradio/flagging.py
gradio/helpers.py
gradio/inputs.py
gradio/interface.py
gradio/interpretation.py
gradio/ipython_ext.py
gradio/layouts.py
gradio/mix.py
gradio/networking.py
gradio/outputs.py
gradio/pipelines.py
gradio/processing_utils.py
gradio/queueing.py
gradio/ranged_response.py
gradio/reload.py
gradio/routes.py
gradio/strings.py
gradio/templates.py
gradio/tunneling.py
gradio/utils.py
gradio/version.txt
gradio/templates/frontend/favicon.png
gradio/templates/frontend/index.html
gradio/templates/frontend/assets/BlockLabel-007567e0.js
gradio/templates/frontend/assets/BlockLabel-007567e0.js.map
gradio/templates/frontend/assets/BlockTitle-ba14a7ea.js
gradio/templates/frontend/assets/BlockTitle-ba14a7ea.js.map
gradio/templates/frontend/assets/Blocks-005a10ea.css
gradio/templates/frontend/assets/Blocks-30072253.js
gradio/templates/frontend/assets/Blocks-30072253.js.map
gradio/templates/frontend/assets/Button-4cd12e76.css
gradio/templates/frontend/assets/Button-56a6eb1f.js
gradio/templates/frontend/assets/Button-56a6eb1f.js.map
gradio/templates/frontend/assets/ColorPicker-76ff4dc7.css
gradio/templates/frontend/assets/ColorPicker.svelte_svelte_type_style_lang-700774cc.js.map
gradio/templates/frontend/assets/Column-2853eb31.css
gradio/templates/frontend/assets/Column-4cfddce1.js
gradio/templates/frontend/assets/Column-4cfddce1.js.map
gradio/templates/frontend/assets/Column.svelte_svelte_type_style_lang-bf454eb5.js.map
gradio/templates/frontend/assets/Copy-b0b737a2.js
gradio/templates/frontend/assets/Copy-b0b737a2.js.map
gradio/templates/frontend/assets/Download-68c405de.js
gradio/templates/frontend/assets/Download-68c405de.js.map
gradio/templates/frontend/assets/DropdownArrow-5fa4dd09.css
gradio_offline-3.31.0.4.dist-info/METADATA
gradio_offline-3.31.0.4.dist-info/WHEEL
gradio_offline-3.31.0.4.dist-info/entry_points.txt
gradio_offline-3.31.0.4.dist-info/licenses/LICENSE
gradio_offline-3.31.0.4.dist-info/RECORD
